LICENSE
MANIFEST.in
README.md
setup.py
bin/muonic
bin/which_tty_daq
muonic/__init__.py
muonic.egg-info/PKG-INFO
muonic.egg-info/SOURCES.txt
muonic.egg-info/dependency_links.txt
muonic.egg-info/requires.txt
muonic.egg-info/top_level.txt
muonic/analysis/__init__.py
muonic/analysis/analyzer.py
muonic/analysis/fit.py
muonic/daq/__init__.py
muonic/daq/connection.py
muonic/daq/exceptions.py
muonic/daq/provider.py
muonic/daq/simdaq.txt
muonic/daq/simulation.py
muonic/gui/__init__.py
muonic/gui/application.py
muonic/gui/daq_commands_help.txt
muonic/gui/dialogs.py
muonic/gui/helpers.py
muonic/gui/muonic.xpm
muonic/gui/plot_canvases.py
muonic/gui/widgets.py
muonic/util/__init__.py
muonic/util/helpers.py
muonic/util/settings_store.py