Metadata-Version: 1.0
Name: muonic
Version: 2.1.3
Summary: Software to work with QNet DAQ cards. This is a TRUNK version
Home-page: https://github.com/CosmicLabDESY/muonic/
Author: Robert Franke, Achim Stoessl, Basho Kaminsky, Martin Ohmann, Hans-Peter Bretz
Author-email: robert.franke@desy.de, achim.stoessl@desy.de, basho.kaminsky@desy.de, martin@mohmann.de, hans-peter.bretz@desy.de
License: GPLv3
Download-URL: https://github.com/CosmicLabDESY/muonic/archive/release2.zip
Keywords: QNET,QuarkNET,Fermilab,DESY,DAQ
Platform: Ubuntu 12.04
Classifier: License :: OSI Approved :: GNU General Public License v3 or later (GPLv3+)
Classifier: Development Status :: 4 - Beta
Classifier: Intended Audience :: Science/Research
Classifier: Intended Audience :: Education
Classifier: Intended Audience :: Developers
Classifier: Programming Language :: Python :: 2.7
Classifier: Programming Language :: Python :: 3
Classifier: Topic :: Scientific/Engineering :: Physics
